pycol_complexity/__init__.py
pycol_complexity/complexity.py
pycol_complexity-1.0.3.dist-info/licenses/LICENSE.txt
pycol_complexity-1.0.3.dist-info/METADATA
pycol_complexity-1.0.3.dist-info/WHEEL
pycol_complexity-1.0.3.dist-info/top_level.txt
pycol_complexity-1.0.3.dist-info/RECORD
