Metadata-Version: 2.4
Name: pycol-complexity
Version: 1.0.3
Summary: Python Package for complexity measures
Author-email: Diogo Apostolo <ogoid.478@gmail.com>
Project-URL: Repository, https://github.com/DiogoApostolo/pycol
Requires-Python: >=3.7
License-File: LICENSE.txt
Requires-Dist: liac-arff>=2.5.0
Requires-Dist: numpy>=1.23
Requires-Dist: pandas>=1.4
Requires-Dist: scikit-learn>=1.1
Requires-Dist: scipy>=1.9
Requires-Dist: matplotlib>=3.7
Dynamic: license-file
